AUTHORS.md
CHANGELOG.md
LICENSE.md
MANIFEST.in
README.rst
runtests.py
setup.cfg
setup.py
django_staticimport.egg-info/PKG-INFO
django_staticimport.egg-info/SOURCES.txt
django_staticimport.egg-info/dependency_links.txt
django_staticimport.egg-info/not-zip-safe
django_staticimport.egg-info/top_level.txt
static_import/__init__.py
static_import/base.py
static_import/settings.py
static_import/management/__init__.py
static_import/management/commands/__init__.py
static_import/management/commands/download_static_file.py
static_import/templates/import.html
static_import/templatetags/__init__.py
static_import/templatetags/staticimport.py